data_basket/__init__.py
data_basket/basket.py
data_basket/exceptions.py
data_basket/shortcuts.py
data_basket/serializers/__init__.py
data_basket/serializers/base.py
data_basket/serializers/builtin_types.py
data_basket/serializers/numpy_types.py
data_basket/serializers/pandas_types.py
data_basket-0.0.6.dist-info/DESCRIPTION.rst
data_basket-0.0.6.dist-info/METADATA
data_basket-0.0.6.dist-info/RECORD
data_basket-0.0.6.dist-info/WHEEL
data_basket-0.0.6.dist-info/metadata.json
data_basket-0.0.6.dist-info/top_level.txt
