Metadata-Version: 2.0
Name: data-basket
Version: 0.0.6
Summary: data basket
Home-page: https://github.com/claydodo/data_basket
Author: claydodo and his little friends (xiao huo ban)
Author-email: claydodo@foxmail.com
License: UNKNOWN
Platform: UNKNOWN
Classifier: Programming Language :: Python :: 2.7 
Classifier: Programming Language :: Python :: 3 
Classifier: Operating System :: OS Independent
